LICENSE.rst
MANIFEST.in
README.md
setup.cfg
setup.py
snprocess/__init__.py
snprocess/__main__.py
snprocess/example.json
snprocess/graph.py
snprocess/logo.png
snprocess/model.py
snprocess.egg-info/PKG-INFO
snprocess.egg-info/SOURCES.txt
snprocess.egg-info/dependency_links.txt
snprocess.egg-info/entry_points.txt
snprocess.egg-info/requires.txt
snprocess.egg-info/top_level.txt
snprocess/qc/MDS_merge.R
snprocess/qc/model.py
snprocess/qc/qc_1.py
snprocess/qc/qc_2.py
snprocess/templates/report_template.html