Metadata-Version: 2.1
Name: snprocess
Version: 1.0.0
Summary: A SNP processing package
Home-page: https://github.com/dokastho/snprocess
Author: Thomas Dokas
Author-email: dokastho@umich.edu
License: UNKNOWN
Platform: UNKNOWN
Classifier: Programming Language :: Python :: 3
Classifier: License :: OSI Approved :: MIT License
Classifier: Operating System :: OS Independent
Requires-Python: >=3.6
